geoid_toolkit/__init__.py
geoid_toolkit/calculate_geoid_undulation.py
geoid_toolkit/calculate_tidal_offset.py
geoid_toolkit/corrected_geoid_undulation.py
geoid_toolkit/gauss_weights.py
geoid_toolkit/geoid_undulation.py
geoid_toolkit/gravity_anomaly.py
geoid_toolkit/gravity_disturbance.py
geoid_toolkit/height_anomaly.py
geoid_toolkit/legendre_polynomials.py
geoid_toolkit/norm_gravity.py
geoid_toolkit/norm_potential.py
geoid_toolkit/read_ICGEM_harmonics.py
geoid_toolkit/read_topography_harmonics.py
geoid_toolkit/real_potential.py
geoid_toolkit/ref_ellipsoid.py
geoid_toolkit/spatial.py
geoid_toolkit/topographic_potential.py
geoid_toolkit/utilities.py
geoid_toolkit/version.py
geoid_toolkit/data/.gitkeep
geoid_toolkit-1.1.2.data/scripts/compute_geoid_grids.py
geoid_toolkit-1.1.2.data/scripts/compute_geoidal_undulation.py
geoid_toolkit-1.1.2.data/scripts/read_EGM2008_geoid_grids.py
geoid_toolkit-1.1.2.data/scripts/read_ICGEM_geoid_grids.py
geoid_toolkit-1.1.2.dist-info/licenses/LICENSE
geoid_toolkit-1.1.2.dist-info/METADATA
geoid_toolkit-1.1.2.dist-info/WHEEL
geoid_toolkit-1.1.2.dist-info/top_level.txt
geoid_toolkit-1.1.2.dist-info/RECORD
