Metadata-Version: 2.4
Name: geoid-toolkit
Version: 1.1.2
Summary: Reads gravity model coefficients and calculates geoid heights
Home-page: https://github.com/tsutterley/geoid-toolkit
Author: Tyler Sutterley
Author-email: tsutterl@uw.edu
License: MIT
Keywords: static gravity field,geoid height,physical geodesy
Classifier: Development Status :: 3 - Alpha
Classifier: Intended Audience :: Science/Research
Classifier: Topic :: Scientific/Engineering :: Physics
Classifier: License :: OSI Approved :: MIT License
Classifier: Programming Language :: Python :: 3
Classifier: Programming Language :: Python :: 3.6
Classifier: Programming Language :: Python :: 3.7
Classifier: Programming Language :: Python :: 3.8
License-File: LICENSE
Requires-Dist: lxml
Requires-Dist: numpy
Requires-Dist: python-dateutil
Dynamic: author
Dynamic: author-email
Dynamic: classifier
Dynamic: description
Dynamic: description-content-type
Dynamic: home-page
Dynamic: keywords
Dynamic: license
Dynamic: license-file
Dynamic: requires-dist
Dynamic: summary
